aws_cli_tool/__init__.py
aws_cli_tool/aws_query.py
tests/__init__.py
tests/test_aws_query.py
aws_cli_tool-0.1.0.dist-info/METADATA
aws_cli_tool-0.1.0.dist-info/WHEEL
aws_cli_tool-0.1.0.dist-info/entry_points.txt
aws_cli_tool-0.1.0.dist-info/top_level.txt
aws_cli_tool-0.1.0.dist-info/RECORD
